README
setup.py
scikits/__init__.py
scikits.example.egg-info/PKG-INFO
scikits.example.egg-info/SOURCES.txt
scikits.example.egg-info/dependency_links.txt
scikits.example.egg-info/namespace_packages.txt
scikits.example.egg-info/requires.txt
scikits.example.egg-info/top_level.txt
scikits.example.egg-info/zip-safe
scikits/example/__init__.py