Metadata-Version: 1.0
Name: scikits.example
Version: 0.1
Summary: Scikits example package
Home-page: http://projects.scipy.org/scipy/scikits
Author: David Cournapeau
Author-email: david@ar.media.kyoto-u.ac.jp
License: MIT
Download-URL: http://projects.scipy.org/scipy/scikits
Platform: UNKNOWN
Classifier: Development Status :: 1 - Planning
Classifier: Environment :: Console
Classifier: Intended Audience :: Developers
Classifier: Intended Audience :: Science/Research
Classifier: License :: OSI Approved :: BSD License
Classifier: Topic :: Scientific/Engineering
